package_hari/__init__.py
package_hari/main.py
package_hari-0.1.0.dist-info/METADATA
package_hari-0.1.0.dist-info/WHEEL
package_hari-0.1.0.dist-info/top_level.txt
package_hari-0.1.0.dist-info/RECORD
