Metadata-Version: 2.1
Name: package_hari
Version: 0.1.0
Summary: for testing
Home-page: 
Author: Hari kowshik
Author-email: harikowshik.molugu@drishyta.ai
Classifier: Programming Language :: Python :: 3
Classifier: License :: OSI Approved :: MIT License
Classifier: Operating System :: OS Independent
Requires-Python: >=3.6
